cntm/__init__.py
cntm/lunar_solar_converter.py
cntm/range_time_enum.py
cntm/string_pre_handler.py
cntm/time_normalizer.py
cntm/time_point.py
cntm/time_unit.py
cntm/resource/holi_lunar.json
cntm/resource/holi_solar.json
cntm/resource/reg.pkl
cntm/resource/regex.txt
tests/test.py
chinatime-1.0.6.dist-info/METADATA
chinatime-1.0.6.dist-info/WHEEL
chinatime-1.0.6.dist-info/top_level.txt
chinatime-1.0.6.dist-info/RECORD
